{
  "id": 10642944,
  "width": 3840,
  "height": 2160,
  "duration": 9,
  "full_res": null,
  "tags": [],
  "url": "https://www.pexels.com/video/close-up-of-preserved-brain-10642944/",
  "image": "https://images.pexels.com/videos/10642944/pexels-photo-10642944.jpeg?auto=compress&cs=tinysrgb&fit=crop&h=630&w=1200",
  "avg_color": null,
  "user": {
    "id": 55956252,
    "name": "Vincuk Konan",
    "url": "https://www.pexels.com/@trashsmash"
  },
  "video_files": [
    {
      "id": 4710005,
      "quality": "hd",
      "file_type": "video/mp4",
      "width": 3840,
      "height": 2160,
      "fps": 29.97,
      "link": "https://videos.pexels.com/video-files/10642944/10642944-hd_3840_2160_30fps.mp4",
      "size": 25195652
    },
    {
      "id": 4710006,
      "quality": "hd",
      "file_type": "video/mp4",
      "width": 2560,
      "height": 1440,
      "fps": 29.97,
      "link": "https://videos.pexels.com/video-files/10642944/10642944-hd_2560_1440_30fps.mp4",
      "size": 15163117
    },
    {
      "id": 4710007,
      "quality": "hd",
      "file_type": "video/mp4",
      "width": 1920,
      "height": 1080,
      "fps": 29.97,
      "link": "https://videos.pexels.com/video-files/10642944/10642944-hd_1920_1080_30fps.mp4",
      "size": 6159554
    },
    {
      "id": 4710008,
      "quality": "sd",
      "file_type": "video/mp4",
      "width": 960,
      "height": 540,
      "fps": 29.97,
      "link": "https://videos.pexels.com/video-files/10642944/10642944-sd_960_540_30fps.mp4",
      "size": 1995260
    },
    {
      "id": 4710009,
      "quality": "hd",
      "file_type": "video/mp4",
      "width": 1280,
      "height": 720,
      "fps": 29.97,
      "link": "https://videos.pexels.com/video-files/10642944/10642944-hd_1280_720_30fps.mp4",
      "size": 3248071
    },
    {
      "id": 4710010,
      "quality": "sd",
      "file_type": "video/mp4",
      "width": 640,
      "height": 360,
      "fps": 29.97,
      "link": "https://videos.pexels.com/video-files/10642944/10642944-sd_640_360_30fps.mp4",
      "size": 691168
    }
  ],
  "video_pictures": [
    {
      "id": 11238545,
      "nr": 0,
      "picture": "https://images.pexels.com/videos/10642944/pictures/preview-0.jpeg"
    },
    {
      "id": 11238549,
      "nr": 1,
      "picture": "https://images.pexels.com/videos/10642944/pictures/preview-1.jpeg"
    },
    {
      "id": 11238551,
      "nr": 2,
      "picture": "https://images.pexels.com/videos/10642944/pictures/preview-2.jpeg"
    },
    {
      "id": 11238553,
      "nr": 3,
      "picture": "https://images.pexels.com/videos/10642944/pictures/preview-3.jpeg"
    },
    {
      "id": 11238559,
      "nr": 4,
      "picture": "https://images.pexels.com/videos/10642944/pictures/preview-4.jpeg"
    },
    {
      "id": 11238567,
      "nr": 5,
      "picture": "https://images.pexels.com/videos/10642944/pictures/preview-5.jpeg"
    },
    {
      "id": 11238573,
      "nr": 6,
      "picture": "https://images.pexels.com/videos/10642944/pictures/preview-6.jpeg"
    },
    {
      "id": 11238576,
      "nr": 7,
      "picture": "https://images.pexels.com/videos/10642944/pictures/preview-7.jpeg"
    },
    {
      "id": 11238579,
      "nr": 8,
      "picture": "https://images.pexels.com/videos/10642944/pictures/preview-8.jpeg"
    },
    {
      "id": 11238581,
      "nr": 9,
      "picture": "https://images.pexels.com/videos/10642944/pictures/preview-9.jpeg"
    },
    {
      "id": 11238582,
      "nr": 10,
      "picture": "https://images.pexels.com/videos/10642944/pictures/preview-10.jpeg"
    },
    {
      "id": 11238584,
      "nr": 11,
      "picture": "https://images.pexels.com/videos/10642944/pictures/preview-11.jpeg"
    },
    {
      "id": 11238588,
      "nr": 12,
      "picture": "https://images.pexels.com/videos/10642944/pictures/preview-12.jpeg"
    },
    {
      "id": 11238591,
      "nr": 13,
      "picture": "https://images.pexels.com/videos/10642944/pictures/preview-13.jpeg"
    },
    {
      "id": 11238594,
      "nr": 14,
      "picture": "https://images.pexels.com/videos/10642944/pictures/preview-14.jpeg"
    }
  ]
}